pylibvpx/__init__.py
pylibvpx/_pylibvpx.cp311-win_amd64.pyd
pylibvpx/_pylibvpx.pyi
pylibvpx/py.typed
pylibvpx-1.0.3.dist-info/METADATA
pylibvpx-1.0.3.dist-info/WHEEL
pylibvpx-1.0.3.dist-info/licenses/LICENSE
pylibvpx-1.0.3.dist-info/RECORD
