Metadata-Version: 2.2
Name: pylibvpx
Version: 1.0.3
Summary: Python bindings for libvpx
Author-Email: =?utf-8?q?Peter_W=C3=BCrtz?= <pwuertz@gmail.com>
Classifier: License :: OSI Approved :: MIT License
Project-URL: Homepage, https://github.com/pwuertz/libvpx-bindings
Requires-Python: >=3.11
